MANIFEST.in
README.md
setup.py
django_timetable.egg-info/PKG-INFO
django_timetable.egg-info/SOURCES.txt
django_timetable.egg-info/dependency_links.txt
django_timetable.egg-info/requires.txt
django_timetable.egg-info/top_level.txt
django_timetable.egg-info/zip-safe
timetable/__init__.py
timetable/admin.py
timetable/models.py
timetable/tests.py
timetable/views.py