Metadata-Version: 1.1
Name: django-timetable
Version: 0.1.3
Summary: An Django app that provides generic calendar functions
Home-page: https://github.com/g3rd/django-timetable
Author: Chad Shryock
Author-email: chad@g3rdmedia.com
License: MIT License
Platform: UNKNOWN
Classifier: Development Status :: 4 - Beta
Classifier: Environment :: Web Environment
Classifier: Framework :: Django
Classifier: Intended Audience :: Developers
Classifier: License :: OSI Approved :: MIT License
Classifier: Operating System :: OS Independent
Classifier: Programming Language :: Python
Classifier: Topic :: Software Development :: Libraries :: Python Modules
Requires: Django (>=1.5)
